{"name":"components","content":{"./components.js":{"id":"./components.js","buildMeta":{"providedExports":true}},"./node_modules/@material/animation/util.js":{"id":"./node_modules/@material/animation/util.js","buildMeta":{"providedExports":true}},"./node_modules/@material/base/component.js":{"id":"./node_modules/@material/base/component.js","buildMeta":{"providedExports":true}},"./node_modules/@material/base/foundation.js":{"id":"./node_modules/@material/base/foundation.js","buildMeta":{"providedExports":true}},"./node_modules/@material/checkbox/component.js":{"id":"./node_modules/@material/checkbox/component.js","buildMeta":{"providedExports":true}},"./node_modules/@material/checkbox/constants.js":{"id":"./node_modules/@material/checkbox/constants.js","buildMeta":{"providedExports":true}},"./node_modules/@material/checkbox/foundation.js":{"id":"./node_modules/@material/checkbox/foundation.js","buildMeta":{"providedExports":true}},"./node_modules/@material/checkbox/index.js":{"id":"./node_modules/@material/checkbox/index.js","buildMeta":{"providedExports":true}},"./node_modules/@material/chips/chip-set/component.js":{"id":"./node_modules/@material/chips/chip-set/component.js","buildMeta":{"providedExports":true}},"./node_modules/@material/chips/chip-set/constants.js":{"id":"./node_modules/@material/chips/chip-set/constants.js","buildMeta":{"providedExports":true}},"./node_modules/@material/chips/chip-set/foundation.js":{"id":"./node_modules/@material/chips/chip-set/foundation.js","buildMeta":{"providedExports":true}},"./node_modules/@material/chips/chip-set/index.js":{"id":"./node_modules/@material/chips/chip-set/index.js","buildMeta":{"providedExports":true}},"./node_modules/@material/chips/chip/component.js":{"id":"./node_modules/@material/chips/chip/component.js","buildMeta":{"providedExports":true}},"./node_modules/@material/chips/chip/constants.js":{"id":"./node_modules/@material/chips/chip/constants.js","buildMeta":{"providedExports":true}},"./node_modules/@material/chips/chip/foundation.js":{"id":"./node_modules/@material/chips/chip/foundation.js","buildMeta":{"providedExports":true}},"./node_modules/@material/chips/chip/index.js":{"id":"./node_modules/@material/chips/chip/index.js","buildMeta":{"providedExports":true}},"./node_modules/@material/chips/index.js":{"id":"./node_modules/@material/chips/index.js","buildMeta":{"providedExports":true}},"./node_modules/@material/data-table/component.js":{"id":"./node_modules/@material/data-table/component.js","buildMeta":{"providedExports":true}},"./node_modules/@material/data-table/constants.js":{"id":"./node_modules/@material/data-table/constants.js","buildMeta":{"providedExports":true}},"./node_modules/@material/data-table/foundation.js":{"id":"./node_modules/@material/data-table/foundation.js","buildMeta":{"providedExports":true}},"./node_modules/@material/data-table/index.js":{"id":"./node_modules/@material/data-table/index.js","buildMeta":{"providedExports":true}},"./node_modules/@material/dialog/component.js":{"id":"./node_modules/@material/dialog/component.js","buildMeta":{"providedExports":true}},"./node_modules/@material/dialog/constants.js":{"id":"./node_modules/@material/dialog/constants.js","buildMeta":{"providedExports":true}},"./node_modules/@material/dialog/foundation.js":{"id":"./node_modules/@material/dialog/foundation.js","buildMeta":{"providedExports":true}},"./node_modules/@material/dialog/index.js":{"id":"./node_modules/@material/dialog/index.js","buildMeta":{"providedExports":true}},"./node_modules/@material/dialog/util.js":{"id":"./node_modules/@material/dialog/util.js","buildMeta":{"providedExports":true}},"./node_modules/@material/dom/events.js":{"id":"./node_modules/@material/dom/events.js","buildMeta":{"providedExports":true}},"./node_modules/@material/dom/ponyfill.js":{"id":"./node_modules/@material/dom/ponyfill.js","buildMeta":{"providedExports":true}},"./node_modules/@material/drawer/component.js":{"id":"./node_modules/@material/drawer/component.js","buildMeta":{"providedExports":true}},"./node_modules/@material/drawer/constants.js":{"id":"./node_modules/@material/drawer/constants.js","buildMeta":{"providedExports":true}},"./node_modules/@material/drawer/dismissible/foundation.js":{"id":"./node_modules/@material/drawer/dismissible/foundation.js","buildMeta":{"providedExports":true}},"./node_modules/@material/drawer/index.js":{"id":"./node_modules/@material/drawer/index.js","buildMeta":{"providedExports":true}},"./node_modules/@material/drawer/modal/foundation.js":{"id":"./node_modules/@material/drawer/modal/foundation.js","buildMeta":{"providedExports":true}},"./node_modules/@material/drawer/util.js":{"id":"./node_modules/@material/drawer/util.js","buildMeta":{"providedExports":true}},"./node_modules/@material/floating-label/component.js":{"id":"./node_modules/@material/floating-label/component.js","buildMeta":{"providedExports":true}},"./node_modules/@material/floating-label/constants.js":{"id":"./node_modules/@material/floating-label/constants.js","buildMeta":{"providedExports":true}},"./node_modules/@material/floating-label/foundation.js":{"id":"./node_modules/@material/floating-label/foundation.js","buildMeta":{"providedExports":true}},"./node_modules/@material/form-field/component.js":{"id":"./node_modules/@material/form-field/component.js","buildMeta":{"providedExports":true}},"./node_modules/@material/form-field/constants.js":{"id":"./node_modules/@material/form-field/constants.js","buildMeta":{"providedExports":true}},"./node_modules/@material/form-field/foundation.js":{"id":"./node_modules/@material/form-field/foundation.js","buildMeta":{"providedExports":true}},"./node_modules/@material/form-field/index.js":{"id":"./node_modules/@material/form-field/index.js","buildMeta":{"providedExports":true}},"./node_modules/@material/icon-button/component.js":{"id":"./node_modules/@material/icon-button/component.js","buildMeta":{"providedExports":true}},"./node_modules/@material/icon-button/constants.js":{"id":"./node_modules/@material/icon-button/constants.js","buildMeta":{"providedExports":true}},"./node_modules/@material/icon-button/foundation.js":{"id":"./node_modules/@material/icon-button/foundation.js","buildMeta":{"providedExports":true}},"./node_modules/@material/icon-button/index.js":{"id":"./node_modules/@material/icon-button/index.js","buildMeta":{"providedExports":true}},"./node_modules/@material/line-ripple/component.js":{"id":"./node_modules/@material/line-ripple/component.js","buildMeta":{"providedExports":true}},"./node_modules/@material/line-ripple/constants.js":{"id":"./node_modules/@material/line-ripple/constants.js","buildMeta":{"providedExports":true}},"./node_modules/@material/line-ripple/foundation.js":{"id":"./node_modules/@material/line-ripple/foundation.js","buildMeta":{"providedExports":true}},"./node_modules/@material/linear-progress/component.js":{"id":"./node_modules/@material/linear-progress/component.js","buildMeta":{"providedExports":true}},"./node_modules/@material/linear-progress/constants.js":{"id":"./node_modules/@material/linear-progress/constants.js","buildMeta":{"providedExports":true}},"./node_modules/@material/linear-progress/foundation.js":{"id":"./node_modules/@material/linear-progress/foundation.js","buildMeta":{"providedExports":true}},"./node_modules/@material/linear-progress/index.js":{"id":"./node_modules/@material/linear-progress/index.js","buildMeta":{"providedExports":true}},"./node_modules/@material/list/component.js":{"id":"./node_modules/@material/list/component.js","buildMeta":{"providedExports":true}},"./node_modules/@material/list/constants.js":{"id":"./node_modules/@material/list/constants.js","buildMeta":{"providedExports":true}},"./node_modules/@material/list/foundation.js":{"id":"./node_modules/@material/list/foundation.js","buildMeta":{"providedExports":true}},"./node_modules/@material/list/index.js":{"id":"./node_modules/@material/list/index.js","buildMeta":{"providedExports":true}},"./node_modules/@material/menu-surface/component.js":{"id":"./node_modules/@material/menu-surface/component.js","buildMeta":{"providedExports":true}},"./node_modules/@material/menu-surface/constants.js":{"id":"./node_modules/@material/menu-surface/constants.js","buildMeta":{"providedExports":true}},"./node_modules/@material/menu-surface/foundation.js":{"id":"./node_modules/@material/menu-surface/foundation.js","buildMeta":{"providedExports":true}},"./node_modules/@material/menu-surface/util.js":{"id":"./node_modules/@material/menu-surface/util.js","buildMeta":{"providedExports":true}},"./node_modules/@material/menu/component.js":{"id":"./node_modules/@material/menu/component.js","buildMeta":{"providedExports":true}},"./node_modules/@material/menu/constants.js":{"id":"./node_modules/@material/menu/constants.js","buildMeta":{"providedExports":true}},"./node_modules/@material/menu/foundation.js":{"id":"./node_modules/@material/menu/foundation.js","buildMeta":{"providedExports":true}},"./node_modules/@material/menu/index.js":{"id":"./node_modules/@material/menu/index.js","buildMeta":{"providedExports":true}},"./node_modules/@material/notched-outline/component.js":{"id":"./node_modules/@material/notched-outline/component.js","buildMeta":{"providedExports":true}},"./node_modules/@material/notched-outline/constants.js":{"id":"./node_modules/@material/notched-outline/constants.js","buildMeta":{"providedExports":true}},"./node_modules/@material/notched-outline/foundation.js":{"id":"./node_modules/@material/notched-outline/foundation.js","buildMeta":{"providedExports":true}},"./node_modules/@material/radio/component.js":{"id":"./node_modules/@material/radio/component.js","buildMeta":{"providedExports":true}},"./node_modules/@material/radio/constants.js":{"id":"./node_modules/@material/radio/constants.js","buildMeta":{"providedExports":true}},"./node_modules/@material/radio/foundation.js":{"id":"./node_modules/@material/radio/foundation.js","buildMeta":{"providedExports":true}},"./node_modules/@material/radio/index.js":{"id":"./node_modules/@material/radio/index.js","buildMeta":{"providedExports":true}},"./node_modules/@material/ripple/component.js":{"id":"./node_modules/@material/ripple/component.js","buildMeta":{"providedExports":true}},"./node_modules/@material/ripple/constants.js":{"id":"./node_modules/@material/ripple/constants.js","buildMeta":{"providedExports":true}},"./node_modules/@material/ripple/foundation.js":{"id":"./node_modules/@material/ripple/foundation.js","buildMeta":{"providedExports":true}},"./node_modules/@material/ripple/index.js":{"id":"./node_modules/@material/ripple/index.js","buildMeta":{"providedExports":true}},"./node_modules/@material/ripple/util.js":{"id":"./node_modules/@material/ripple/util.js","buildMeta":{"providedExports":true}},"./node_modules/@material/select/component.js":{"id":"./node_modules/@material/select/component.js","buildMeta":{"providedExports":true}},"./node_modules/@material/select/constants.js":{"id":"./node_modules/@material/select/constants.js","buildMeta":{"providedExports":true}},"./node_modules/@material/select/foundation.js":{"id":"./node_modules/@material/select/foundation.js","buildMeta":{"providedExports":true}},"./node_modules/@material/select/helper-text/component.js":{"id":"./node_modules/@material/select/helper-text/component.js","buildMeta":{"providedExports":true}},"./node_modules/@material/select/helper-text/constants.js":{"id":"./node_modules/@material/select/helper-text/constants.js","buildMeta":{"providedExports":true}},"./node_modules/@material/select/helper-text/foundation.js":{"id":"./node_modules/@material/select/helper-text/foundation.js","buildMeta":{"providedExports":true}},"./node_modules/@material/select/helper-text/index.js":{"id":"./node_modules/@material/select/helper-text/index.js","buildMeta":{"providedExports":true}},"./node_modules/@material/select/icon/component.js":{"id":"./node_modules/@material/select/icon/component.js","buildMeta":{"providedExports":true}},"./node_modules/@material/select/icon/constants.js":{"id":"./node_modules/@material/select/icon/constants.js","buildMeta":{"providedExports":true}},"./node_modules/@material/select/icon/foundation.js":{"id":"./node_modules/@material/select/icon/foundation.js","buildMeta":{"providedExports":true}},"./node_modules/@material/select/icon/index.js":{"id":"./node_modules/@material/select/icon/index.js","buildMeta":{"providedExports":true}},"./node_modules/@material/select/index.js":{"id":"./node_modules/@material/select/index.js","buildMeta":{"providedExports":true}},"./node_modules/@material/slider/component.js":{"id":"./node_modules/@material/slider/component.js","buildMeta":{"providedExports":true}},"./node_modules/@material/slider/constants.js":{"id":"./node_modules/@material/slider/constants.js","buildMeta":{"providedExports":true}},"./node_modules/@material/slider/foundation.js":{"id":"./node_modules/@material/slider/foundation.js","buildMeta":{"providedExports":true}},"./node_modules/@material/slider/index.js":{"id":"./node_modules/@material/slider/index.js","buildMeta":{"providedExports":true}},"./node_modules/@material/snackbar/component.js":{"id":"./node_modules/@material/snackbar/component.js","buildMeta":{"providedExports":true}},"./node_modules/@material/snackbar/constants.js":{"id":"./node_modules/@material/snackbar/constants.js","buildMeta":{"providedExports":true}},"./node_modules/@material/snackbar/foundation.js":{"id":"./node_modules/@material/snackbar/foundation.js","buildMeta":{"providedExports":true}},"./node_modules/@material/snackbar/index.js":{"id":"./node_modules/@material/snackbar/index.js","buildMeta":{"providedExports":true}},"./node_modules/@material/snackbar/util.js":{"id":"./node_modules/@material/snackbar/util.js","buildMeta":{"providedExports":true}},"./node_modules/@material/switch/component.js":{"id":"./node_modules/@material/switch/component.js","buildMeta":{"providedExports":true}},"./node_modules/@material/switch/constants.js":{"id":"./node_modules/@material/switch/constants.js","buildMeta":{"providedExports":true}},"./node_modules/@material/switch/foundation.js":{"id":"./node_modules/@material/switch/foundation.js","buildMeta":{"providedExports":true}},"./node_modules/@material/switch/index.js":{"id":"./node_modules/@material/switch/index.js","buildMeta":{"providedExports":true}},"./node_modules/@material/tab-bar/component.js":{"id":"./node_modules/@material/tab-bar/component.js","buildMeta":{"providedExports":true}},"./node_modules/@material/tab-bar/constants.js":{"id":"./node_modules/@material/tab-bar/constants.js","buildMeta":{"providedExports":true}},"./node_modules/@material/tab-bar/foundation.js":{"id":"./node_modules/@material/tab-bar/foundation.js","buildMeta":{"providedExports":true}},"./node_modules/@material/tab-bar/index.js":{"id":"./node_modules/@material/tab-bar/index.js","buildMeta":{"providedExports":true}},"./node_modules/@material/tab-indicator/component.js":{"id":"./node_modules/@material/tab-indicator/component.js","buildMeta":{"providedExports":true}},"./node_modules/@material/tab-indicator/constants.js":{"id":"./node_modules/@material/tab-indicator/constants.js","buildMeta":{"providedExports":true}},"./node_modules/@material/tab-indicator/fading-foundation.js":{"id":"./node_modules/@material/tab-indicator/fading-foundation.js","buildMeta":{"providedExports":true}},"./node_modules/@material/tab-indicator/foundation.js":{"id":"./node_modules/@material/tab-indicator/foundation.js","buildMeta":{"providedExports":true}},"./node_modules/@material/tab-indicator/sliding-foundation.js":{"id":"./node_modules/@material/tab-indicator/sliding-foundation.js","buildMeta":{"providedExports":true}},"./node_modules/@material/tab-scroller/component.js":{"id":"./node_modules/@material/tab-scroller/component.js","buildMeta":{"providedExports":true}},"./node_modules/@material/tab-scroller/constants.js":{"id":"./node_modules/@material/tab-scroller/constants.js","buildMeta":{"providedExports":true}},"./node_modules/@material/tab-scroller/foundation.js":{"id":"./node_modules/@material/tab-scroller/foundation.js","buildMeta":{"providedExports":true}},"./node_modules/@material/tab-scroller/rtl-default-scroller.js":{"id":"./node_modules/@material/tab-scroller/rtl-default-scroller.js","buildMeta":{"providedExports":true}},"./node_modules/@material/tab-scroller/rtl-negative-scroller.js":{"id":"./node_modules/@material/tab-scroller/rtl-negative-scroller.js","buildMeta":{"providedExports":true}},"./node_modules/@material/tab-scroller/rtl-reverse-scroller.js":{"id":"./node_modules/@material/tab-scroller/rtl-reverse-scroller.js","buildMeta":{"providedExports":true}},"./node_modules/@material/tab-scroller/rtl-scroller.js":{"id":"./node_modules/@material/tab-scroller/rtl-scroller.js","buildMeta":{"providedExports":true}},"./node_modules/@material/tab-scroller/util.js":{"id":"./node_modules/@material/tab-scroller/util.js","buildMeta":{"providedExports":true}},"./node_modules/@material/tab/component.js":{"id":"./node_modules/@material/tab/component.js","buildMeta":{"providedExports":true}},"./node_modules/@material/tab/constants.js":{"id":"./node_modules/@material/tab/constants.js","buildMeta":{"providedExports":true}},"./node_modules/@material/tab/foundation.js":{"id":"./node_modules/@material/tab/foundation.js","buildMeta":{"providedExports":true}},"./node_modules/@material/textfield/character-counter/component.js":{"id":"./node_modules/@material/textfield/character-counter/component.js","buildMeta":{"providedExports":true}},"./node_modules/@material/textfield/character-counter/constants.js":{"id":"./node_modules/@material/textfield/character-counter/constants.js","buildMeta":{"providedExports":true}},"./node_modules/@material/textfield/character-counter/foundation.js":{"id":"./node_modules/@material/textfield/character-counter/foundation.js","buildMeta":{"providedExports":true}},"./node_modules/@material/textfield/character-counter/index.js":{"id":"./node_modules/@material/textfield/character-counter/index.js","buildMeta":{"providedExports":true}},"./node_modules/@material/textfield/component.js":{"id":"./node_modules/@material/textfield/component.js","buildMeta":{"providedExports":true}},"./node_modules/@material/textfield/constants.js":{"id":"./node_modules/@material/textfield/constants.js","buildMeta":{"providedExports":true}},"./node_modules/@material/textfield/foundation.js":{"id":"./node_modules/@material/textfield/foundation.js","buildMeta":{"providedExports":true}},"./node_modules/@material/textfield/helper-text/component.js":{"id":"./node_modules/@material/textfield/helper-text/component.js","buildMeta":{"providedExports":true}},"./node_modules/@material/textfield/helper-text/constants.js":{"id":"./node_modules/@material/textfield/helper-text/constants.js","buildMeta":{"providedExports":true}},"./node_modules/@material/textfield/helper-text/foundation.js":{"id":"./node_modules/@material/textfield/helper-text/foundation.js","buildMeta":{"providedExports":true}},"./node_modules/@material/textfield/helper-text/index.js":{"id":"./node_modules/@material/textfield/helper-text/index.js","buildMeta":{"providedExports":true}},"./node_modules/@material/textfield/icon/component.js":{"id":"./node_modules/@material/textfield/icon/component.js","buildMeta":{"providedExports":true}},"./node_modules/@material/textfield/icon/constants.js":{"id":"./node_modules/@material/textfield/icon/constants.js","buildMeta":{"providedExports":true}},"./node_modules/@material/textfield/icon/foundation.js":{"id":"./node_modules/@material/textfield/icon/foundation.js","buildMeta":{"providedExports":true}},"./node_modules/@material/textfield/icon/index.js":{"id":"./node_modules/@material/textfield/icon/index.js","buildMeta":{"providedExports":true}},"./node_modules/@material/textfield/index.js":{"id":"./node_modules/@material/textfield/index.js","buildMeta":{"providedExports":true}},"./node_modules/@material/top-app-bar/component.js":{"id":"./node_modules/@material/top-app-bar/component.js","buildMeta":{"providedExports":true}},"./node_modules/@material/top-app-bar/constants.js":{"id":"./node_modules/@material/top-app-bar/constants.js","buildMeta":{"providedExports":true}},"./node_modules/@material/top-app-bar/fixed/foundation.js":{"id":"./node_modules/@material/top-app-bar/fixed/foundation.js","buildMeta":{"providedExports":true}},"./node_modules/@material/top-app-bar/foundation.js":{"id":"./node_modules/@material/top-app-bar/foundation.js","buildMeta":{"providedExports":true}},"./node_modules/@material/top-app-bar/index.js":{"id":"./node_modules/@material/top-app-bar/index.js","buildMeta":{"providedExports":true}},"./node_modules/@material/top-app-bar/short/foundation.js":{"id":"./node_modules/@material/top-app-bar/short/foundation.js","buildMeta":{"providedExports":true}},"./node_modules/@material/top-app-bar/standard/foundation.js":{"id":"./node_modules/@material/top-app-bar/standard/foundation.js","buildMeta":{"providedExports":true}},"./node_modules/focus-trap/index.js":{"id":"./node_modules/focus-trap/index.js","buildMeta":{"providedExports":true}},"./node_modules/tabbable/index.js":{"id":"./node_modules/tabbable/index.js","buildMeta":{"providedExports":true}},"./node_modules/tslib/tslib.es6.js":{"id":"./node_modules/tslib/tslib.es6.js","buildMeta":{"providedExports":true}},"./node_modules/xtend/immutable.js":{"id":"./node_modules/xtend/immutable.js","buildMeta":{"providedExports":true}}}}